jl95/pytools/gitv.py
jl95/pytools/gitvpyproject.py
jl95terceira_pytools_git-1.0.0.dist-info/METADATA
jl95terceira_pytools_git-1.0.0.dist-info/WHEEL
jl95terceira_pytools_git-1.0.0.dist-info/entry_points.txt
jl95terceira_pytools_git-1.0.0.dist-info/RECORD
