Metadata-Version: 2.4
Name: jl95terceira_pytools_git
Version: 1.0.0
Summary: Python command line tools collection - GIT
Project-URL: Homepage, https://github.com/jl95terceira/project-pytools-git
Project-URL: Issues, https://github.com/jl95terceira/project-pytools-git/issues
Author-email: Joao Luis Ornelas da Silva <jl95terceira@gmail.com>
Classifier: License :: OSI Approved :: MIT License
Classifier: Operating System :: OS Independent
Classifier: Programming Language :: Python :: 3
Requires-Python: >=3.12
Requires-Dist: jl95terceira-batteries>=1.7.1
Requires-Dist: jl95terceira-pytools-env-git>=0.1.3
